cryptcha/__init__.py
cryptcha-0.0.2.dist-info/WHEEL
cryptcha-0.0.2.dist-info/METADATA
cryptcha-0.0.2.dist-info/RECORD
